Workbook

Sheet Simulador
B7: Patrimônio Acumulado
B9: * Preencha os campos abaixo para realizar as simulações financeiras
B10: Investimento Mensal
B11: Quanto você deseja investir por mês? | C11: 200
B12: Por quantos anos deseja investir? | C12: 5
B13: Qual a Taxa de rendimento mensal? | C13: 0.01079
B15: Patrimônio acumulado? | C15: =FV(C13,C12*12,C11*-1) -> 16755.383
B16: Dividendos mensais? | C16: =C15*Configurações!$C$10 -> 100.5323
B19: Cenários
B20: * Simulação de cenários com base nos dados informados
B21: Períodos | C21: Patrimônico Acumulado | D21: Dividendos
B22: 02 Anos | C22: =FV($C$13,(LEFT(B22,3)*12),$C$11*-1) -> 5445.5255 | D22: =C22*Configurações!$C$10 -> 32.673153
B23: 05 Anos | C23: =FV($C$13,(LEFT(B23,3)*12),$C$11*-1) -> 16755.383 | D23: =C23*Configurações!$C$10 -> 100.5323
B24: 10 Anos | C24: =FV($C$13,(LEFT(B24,3)*12),$C$11*-1) -> 48656.843 | D24: =C24*Configurações!$C$10 -> 291.94106
B25: 20 Anos | C25: =FV($C$13,(LEFT(B25,3)*12),$C$11*-1) -> 225039.68 | D25: =C25*Configurações!$C$10 -> 1350.2381
B26: 30 Anos | C26: =FV($C$13,(LEFT(B26,3)*12),$C$11*-1) -> 864433.93 | D26: =C26*Configurações!$C$10 -> 5186.6036
B29: Sugestão de Carteira
B31: Perfil do Investidor | C31: =Configurações!C14 -> Agressivo
B32: Valor do Investimento Mensal | C32: =$C$11 -> 200
B34: Tipos de FII | C34: Sugestão de Percentual | D34: Valores
B35: Papel | C35: =VLOOKUP($C$31&"-"&B35,Configurações!$M$9:$P$27,4,FALSE) -> 0.5 | D35: =C35*$C$32 -> 100
B36: Tijolo | C36: =VLOOKUP($C$31&"-"&B36,Configurações!$M$9:$P$27,4,FALSE) -> 0.1 | D36: =C36*$C$32 -> 20
B37: Híbridos | C37: =VLOOKUP($C$31&"-"&B37,Configurações!$M$9:$P$27,4,FALSE) -> 0.05 | D37: =C37*$C$32 -> 10
B38: FOF's | C38: =VLOOKUP($C$31&"-"&B38,Configurações!$M$9:$P$27,4,FALSE) -> 0.05 | D38: =C38*$C$32 -> 10
B39: Desenvolvimento | C39: =VLOOKUP($C$31&"-"&B39,Configurações!$M$9:$P$27,4,FALSE) -> 0.2 | D39: =C39*$C$32 -> 40
B40: Hotelarias | C40: =VLOOKUP($C$31&"-"&B40,Configurações!$M$9:$P$27,4,FALSE) -> 0.1 | D40: =C40*$C$32 -> 20
D41: =SUM(D35:D40) -> 200

Sheet Configurações
B7: Configurações
B9: Salário Mensal | C9: 2000 | M9: Chave | N9: Perfil | O9: Tipos de FII | P9: %
B10: Redimento da Carteira | C10: 0.006 | M10: =N10&"-"&O10 -> Conservador-Papel | N10: Conservador | O10: Papel | P10: 0.3
B11: Percentual Destinado a Investimento | C11: 0.3 | M11: =N11&"-"&O11 -> Conservador-Tijolo | N11: Conservador | O11: Tijolo | P11: 0.5
B12: Sugestões de Investimento | C12: =C9*C11 -> 600 | M12: =N12&"-"&O12 -> Conservador-Híbridos | N12: Conservador | O12: Híbridos | P12: 0.1
M13: =N13&"-"&O13 -> Conservador-FOF's | N13: Conservador | O13: FOF's | P13: 0.1
B14: Perfil de Investidor | C14: Agressivo | M14: =N14&"-"&O14 -> Conservador-Desenvolvimento | N14: Conservador | O14: Desenvolvimento | P14: 0
M15: =N15&"-"&O15 -> Conservador-Hotelarias | N15: Conservador | O15: Hotelarias | P15: 0
M16: =N16&"-"&O16 -> Moderado-Papel | N16: Moderado | O16: Papel | P16: 0.32
M17: =N17&"-"&O17 -> Moderado-Tijolo | N17: Moderado | O17: Tijolo | P17: 0.35
M18: =N18&"-"&O18 -> Moderado-Híbridos | N18: Moderado | O18: Híbridos | P18: 0.08
M19: =N19&"-"&O19 -> Moderado-FOF's | N19: Moderado | O19: FOF's | P19: 0.05
M20: =N20&"-"&O20 -> Moderado-Desenvolvimento | N20: Moderado | O20: Desenvolvimento | P20: 0.1
M21: =N21&"-"&O21 -> Moderado-Hotelarias | N21: Moderado | O21: Hotelarias | P21: 0.1
M22: =N22&"-"&O22 -> Agressivo-Papel | N22: Agressivo | O22: Papel | P22: 0.5
M23: =N23&"-"&O23 -> Agressivo-Tijolo | N23: Agressivo | O23: Tijolo | P23: 0.1
M24: =N24&"-"&O24 -> Agressivo-Híbridos | N24: Agressivo | O24: Híbridos | P24: 0.05
M25: =N25&"-"&O25 -> Agressivo-FOF's | N25: Agressivo | O25: FOF's | P25: 0.05
M26: =N26&"-"&O26 -> Agressivo-Desenvolvimento | N26: Agressivo | O26: Desenvolvimento | P26: 0.2
M27: =N27&"-"&O27 -> Agressivo-Hotelarias | N27: Agressivo | O27: Hotelarias | P27: 0.1
